lpsn/__init__.py
lpsn/client.py
lpsn-1.0.0.dist-info/LICENSE
lpsn-1.0.0.dist-info/METADATA
lpsn-1.0.0.dist-info/WHEEL
lpsn-1.0.0.dist-info/top_level.txt
lpsn-1.0.0.dist-info/RECORD
