Metadata-Version: 2.1
Name: lpsn
Version: 1.0.0
Summary: LPSN-API - Programmatic Access to LPSN
Home-page: https://lpsn.dsmz.de/
Author: Julia Koblitz
Author-email: julia.koblitz@dsmz.de
Keywords: microbiology taxonomy nomenclature bacteria archaea
Classifier: License :: OSI Approved :: MIT License
Classifier: Programming Language :: Python :: 3
Classifier: Intended Audience :: Science/Research
Classifier: Topic :: Scientific/Engineering :: Bio-Informatics
Requires-Python: >=3.6
License-File: LICENSE
Requires-Dist: python-keycloak
Requires-Dist: requests >=2.25.1
Requires-Dist: urllib3 >=1.26.5
